mitm_tooling/__init__.py
mitm_tooling/data_types/__init__.py
mitm_tooling/data_types/convert.py
mitm_tooling/data_types/data_types.py
mitm_tooling/definition/__init__.py
mitm_tooling/definition/definition_representation.py
mitm_tooling/definition/definition_tools.py
mitm_tooling/definition/maed.yaml
mitm_tooling/definition/oced.yaml
mitm_tooling/definition/ppd.yaml
mitm_tooling/definition/registry.py
mitm_tooling/extraction/__init__.py
mitm_tooling/extraction/anything/__init__.py
mitm_tooling/extraction/anything/conversion_context.py
mitm_tooling/extraction/relational/__init__.py
mitm_tooling/extraction/relational/common.py
mitm_tooling/extraction/relational/data_models/__init__.py
mitm_tooling/extraction/relational/data_models/compiled.py
mitm_tooling/extraction/relational/data_models/db_meta.py
mitm_tooling/extraction/relational/data_models/db_probe.py
mitm_tooling/extraction/relational/data_models/probe_models.py
mitm_tooling/extraction/relational/data_models/table_identifiers.py
mitm_tooling/extraction/relational/data_models/virtual_view.py
mitm_tooling/extraction/relational/data_models/base/__init__.py
mitm_tooling/extraction/relational/db/__init__.py
mitm_tooling/extraction/relational/db/db_meta_edit.py
mitm_tooling/extraction/relational/db/db_probing.py
mitm_tooling/extraction/relational/db/db_reflection.py
mitm_tooling/extraction/relational/db/db_schema_query.py
mitm_tooling/extraction/relational/mapping/__init__.py
mitm_tooling/extraction/relational/mapping/concept_mapping.py
mitm_tooling/extraction/relational/mapping/db_mapping.py
mitm_tooling/extraction/relational/mapping/export.py
mitm_tooling/extraction/relational/mapping/validation_models.py
mitm_tooling/extraction/relational/transformation/__init__.py
mitm_tooling/extraction/relational/transformation/db_transformation.py
mitm_tooling/extraction/relational/transformation/df_transformation.py
mitm_tooling/extraction/relational/transformation/post_processing.py
mitm_tooling-0.10.6.dist-info/METADATA
mitm_tooling-0.10.6.dist-info/WHEEL
mitm_tooling-0.10.6.dist-info/licenses/LICENSE
mitm_tooling-0.10.6.dist-info/RECORD
