Metadata-Version: 2.4
Name: mitm-tooling
Version: 0.10.6
Author-email: Leah Tacke Genannt Unterberg <l.tgu@pads.rwth-aachen.de>
License: MIT License
License-File: LICENSE
Requires-Python: <3.14,>=3.12
Requires-Dist: alembic<2,>=1.16
Requires-Dist: genson>=1.3.0
Requires-Dist: numpy<3,>=2
Requires-Dist: pandas[compression,computation,performance]<3,>=2
Requires-Dist: pydantic<3,>=2.11
Requires-Dist: ruamel-yaml>=0.18
Requires-Dist: sqlalchemy-utils<1,>=0.38.0
Requires-Dist: sqlalchemy<3,>=2
Requires-Dist: stream-zip<0.1.0,>=0.0.8
Provides-Extra: pm
Requires-Dist: pm4py; extra == 'pm'
